src/__init__.py
src/cli/__init__.py
src/cli/analyze_patch.py
src/cli/tags.py
src/cli/viewless_suites.py
src/utils/__init__.py
src/utils/cli_args.py
src/utils/tags.py
evergreen_scripts-0.5.1.dist-info/entry_points.txt
evergreen_scripts-0.5.1.dist-info/LICENSE
evergreen_scripts-0.5.1.dist-info/WHEEL
evergreen_scripts-0.5.1.dist-info/METADATA
evergreen_scripts-0.5.1.dist-info/RECORD
